Metadata-Version: 2.1
Name: netmiko
Version: 4.1.2
Summary: Multi-vendor library to simplify legacy CLI connections to network devices
Home-page: https://github.com/ktbyers/netmiko
Author: Kirk Byers
Author-email: ktbyers@twb-tech.com
License: MIT
Platform: UNKNOWN
Classifier: License :: OSI Approved :: MIT License
Classifier: Programming Language :: Python :: 3
Classifier: Programming Language :: Python :: 3.7
Classifier: Programming Language :: Python :: 3.8
Classifier: Programming Language :: Python :: 3.9
Classifier: Programming Language :: Python :: 3.10
License-File: LICENSE
